integrify/clopos/__init__.py
integrify/clopos/client.py
integrify/clopos/env.py
integrify/clopos/handlers.py
integrify/clopos/helpers.py
integrify/clopos/py.typed
integrify/clopos/schemas/__init__.py
integrify/clopos/schemas/enums.py
integrify/clopos/schemas/auth/__init__.py
integrify/clopos/schemas/auth/request.py
integrify/clopos/schemas/auth/response.py
integrify/clopos/schemas/categories/__init__.py
integrify/clopos/schemas/categories/object.py
integrify/clopos/schemas/categories/request.py
integrify/clopos/schemas/common/__init__.py
integrify/clopos/schemas/common/object.py
integrify/clopos/schemas/common/request.py
integrify/clopos/schemas/common/response.py
integrify/clopos/schemas/customers/__init__.py
integrify/clopos/schemas/customers/object.py
integrify/clopos/schemas/customers/request.py
integrify/clopos/schemas/orders/__init__.py
integrify/clopos/schemas/orders/object.py
integrify/clopos/schemas/orders/request.py
integrify/clopos/schemas/products/__init__.py
integrify/clopos/schemas/products/object.py
integrify/clopos/schemas/products/request.py
integrify/clopos/schemas/receipts/__init__.py
integrify/clopos/schemas/receipts/object.py
integrify/clopos/schemas/receipts/request.py
integrify/clopos/schemas/sales/__init__.py
integrify/clopos/schemas/sales/object.py
integrify/clopos/schemas/stations/__init__.py
integrify/clopos/schemas/stations/object.py
integrify/clopos/schemas/stations/request.py
integrify/clopos/schemas/users/__init__.py
integrify/clopos/schemas/users/object.py
integrify/clopos/schemas/venues/__init__.py
integrify/clopos/schemas/venues/object.py
integrify_clopos-0.0.1.dist-info/METADATA
integrify_clopos-0.0.1.dist-info/WHEEL
integrify_clopos-0.0.1.dist-info/licenses/LICENSE
integrify_clopos-0.0.1.dist-info/RECORD
